auth_protection/__init__.py
auth_protection/admin.py
auth_protection/apps.py
auth_protection/authentications.py
auth_protection/models.py
auth_protection/serializers.py
auth_protection/tests.py
auth_protection/utils.py
auth_protection/views.py
django_auth_protection-1.0.3.dist-info/LICENSE
django_auth_protection-1.0.3.dist-info/METADATA
django_auth_protection-1.0.3.dist-info/WHEEL
django_auth_protection-1.0.3.dist-info/top_level.txt
django_auth_protection-1.0.3.dist-info/RECORD
